cli/__init__.py
cli/__main__.py
cli/config.py
cli/commands/__init__.py
cli/commands/agents.py
cli/commands/events.py
cli/commands/fix_embeddings.py
cli/commands/init.py
cli/commands/status.py
cli/commands/tasks.py
cli/commands/upgrade.py
cli/helpers/__init__.py
cli/helpers/check_github_for_latest_version.py
cli/helpers/check_mind_status_in_directory.py
cli/helpers/copy_capabilities_to_target.py
cli/helpers/copy_ecosystem_templates_to_target.py
cli/helpers/copy_runtime_package_to_target.py
cli/helpers/create_ai_config_files_for_claude_agents_gemini.py
cli/helpers/create_database_config_yaml.py
cli/helpers/create_env_example_file.py
cli/helpers/create_mcp_config_json.py
cli/helpers/fix_embeddings_for_nodes_and_links.py
cli/helpers/generate_embeddings_for_graph_nodes.py
cli/helpers/generate_repo_overview_maps.py
cli/helpers/get_mcp_version_from_config.py
cli/helpers/get_paths_for_templates_and_runtime.py
cli/helpers/ingest_capabilities_to_graph.py
cli/helpers/ingest_repo_files_to_graph.py
cli/helpers/inject_agents_to_graph.py
cli/helpers/inject_seed_yaml_to_graph.py
cli/helpers/setup_database_and_apply_schema.py
cli/helpers/show_upgrade_notice_if_available.py
cli/helpers/sync_skills_to_ai_tool_directories.py
cli/helpers/update_gitignore_with_runtime_entry.py
cli/helpers/validate_embedding_config_matches_stored.py
connectome/README.md
connectome/index.ts
connectome/package-lock.json
connectome/package.json
connectome/tsconfig.json
connectome/adapters/index.ts
connectome/adapters/local.ts
connectome/adapters/remote.ts
connectome/core/index.ts
connectome/core/types/adapter.ts
connectome/core/types/index.ts
connectome/core/types/schema.ts
connectome/node_modules/.package-lock.json
connectome/node_modules/.bin/js-yaml
connectome/node_modules/.bin/loose-envify
connectome/node_modules/.bin/tsc
connectome/node_modules/.bin/tsserver
connectome/node_modules/@types/d3-color/LICENSE
connectome/node_modules/@types/d3-color/README.md
mind_mcp-0.2.0.dist-info/METADATA
mind_mcp-0.2.0.dist-info/WHEEL
mind_mcp-0.2.0.dist-info/entry_points.txt
mind_mcp-0.2.0.dist-info/RECORD
