Metadata-Version: 2.4
Name: mind-mcp
Version: 0.2.0
Summary: MIND Engine — Graph physics, traversal, client
Author-email: Mindforge <hello@mindforge.ai>
License: MIT
Requires-Python: >=3.10
Requires-Dist: falkordb>=1.0.0
Requires-Dist: fastapi>=0.100.0
Requires-Dist: httpx>=0.24.0
Requires-Dist: neo4j>=5.0.0
Requires-Dist: numpy>=1.24.0
Requires-Dist: pydantic>=2.0.0
Requires-Dist: pyyaml>=6.0
Requires-Dist: websockets>=11.0
Provides-Extra: dev
Requires-Dist: pytest-asyncio>=0.21.0; extra == 'dev'
Requires-Dist: pytest>=7.0.0; extra == 'dev'
